.editorconfig
.gitignore
.travis.yml
CONTRIBUTING.rst
HISTORY.rst
LICENSE
MANIFEST.in
Makefile
README.rst
requirements_dev.txt
setup.cfg
setup.py
tox.ini
.github/ISSUE_TEMPLATE.md
discosuck/__init__.py
discosuck/cli.py
discosuck/discosuck.py
discosuck.egg-info/PKG-INFO
discosuck.egg-info/SOURCES.txt
discosuck.egg-info/dependency_links.txt
discosuck.egg-info/entry_points.txt
discosuck.egg-info/not-zip-safe
discosuck.egg-info/requires.txt
discosuck.egg-info/top_level.txt
docs/Makefile
docs/conf.py
docs/contributing.rst
docs/history.rst
docs/index.rst
docs/installation.rst
docs/make.bat
docs/readme.rst
docs/usage.rst
tests/__init__.py
tests/test_discosuck.py