Metadata-Version: 2.1
Name: discosuck
Version: 0.1.0
Summary: Suck posts from a Discourse forum.
Home-page: https://github.com/devbisme/discosuck
Author: Dave Vandenbout
Author-email: devb@xess.com
License: MIT license
Project-URL: Documentation, https://github.com/devbisme/discosuck
Project-URL: Source, https://github.com/devbisme/discosuck
Project-URL: Changelog, https://github.com/devbisme/discosuck/blob/master/HISTORY.rst
Project-URL: Tracker, https://github.com/devbisme/discosuck/issues
Keywords: discosuck
Classifier: Development Status :: 2 - Pre-Alpha
Classifier: Intended Audience :: Developers
Classifier: License :: OSI Approved :: MIT License
Classifier: Natural Language :: English
Classifier: Programming Language :: Python :: 3
Classifier: Programming Language :: Python :: 3.6
Classifier: Programming Language :: Python :: 3.7
Classifier: Programming Language :: Python :: 3.8
Requires-Python: >=3.6
License-File: LICENSE
